dcm_processor_lib/__init__.py
dcm_processor_lib/env_vars.py
dcm_processor_lib/logging.py
dcm_processor_lib-0.4.3.dist-info/LICENSE
dcm_processor_lib-0.4.3.dist-info/METADATA
dcm_processor_lib-0.4.3.dist-info/WHEEL
dcm_processor_lib-0.4.3.dist-info/top_level.txt
dcm_processor_lib-0.4.3.dist-info/RECORD
